unique_quartr/constants/document_types.py
unique_quartr/constants/event_types.py
unique_quartr/endpoints/api.py
unique_quartr/endpoints/schemas.py
unique_quartr/service.py
unique_quartr/settings.py
unique_quartr/transcripts/earnings_call/__init__.py
unique_quartr/transcripts/earnings_call/schema.py
unique_quartr/transcripts/earnings_call/transcript_template.j2
unique_quartr-0.2.5.dist-info/LICENSE
unique_quartr-0.2.5.dist-info/METADATA
unique_quartr-0.2.5.dist-info/WHEEL
unique_quartr-0.2.5.dist-info/RECORD
