Metadata-Version: 2.3
Name: unique_quartr
Version: 0.2.5
Summary: Unique Quartr API client
License: Proprietary
Author: Rami Azouz
Author-email: rami.ext@unique.ch
Requires-Python: >=3.12,<4.0
Classifier: License :: Other/Proprietary License
Classifier: Programming Language :: Python :: 3
Classifier: Programming Language :: Python :: 3.12
Classifier: Programming Language :: Python :: 3.13
Requires-Dist: httpx (>=0.28.0,<0.29.0)
Requires-Dist: jinja2 (>=3.1.0,<4.0.0)
Requires-Dist: pydantic (>=2.12.4,<3.0.0)
Requires-Dist: pydantic-settings (>=2.10.1,<3.0.0)
Requires-Dist: requests (>=2.32.0,<3.0.0)
Requires-Dist: unique-toolkit (>=1.38.1,<2.0.0)
